polyhorner/__init__.py
polyhorner/polyhorner.py
polyhorner-1.1.0.dist-info/LICENSE
polyhorner-1.1.0.dist-info/METADATA
polyhorner-1.1.0.dist-info/WHEEL
polyhorner-1.1.0.dist-info/top_level.txt
polyhorner-1.1.0.dist-info/RECORD
