Metadata-Version: 2.1
Name: polyhorner
Version: 1.1.0
Summary: Will build univariate using an optimized Horner method and multivariate polynomial using a somewhat optimized Horner method 
Home-page: https://github.com/IDontReallyCode/polyhorner
Author: IDontReallyCode
Author-email: idontreallycode@outlook.com
License: MIT
Platform: UNKNOWN
License-File: LICENSE
Requires-Dist: numpy
Requires-Dist: numba
